ceppy/__init__.py
ceppy/adapters/__init__.py
ceppy/adapters/aiohttp_client.py
ceppy/cep_data.py
ceppy/cep_service_loader.py
ceppy/ceppy.py
ceppy/protocols/__init__.py
ceppy/protocols/http_client.py
ceppy/protocols/query_service.py
ceppy/protocols/service_loader.py
ceppy/services/__init__.py
ceppy/services/correios.py
ceppy/services/opencep.py
ceppy/services/viacep.py
ceppy-1.0.1.dist-info/LICENSE.md
ceppy-1.0.1.dist-info/METADATA
ceppy-1.0.1.dist-info/WHEEL
ceppy-1.0.1.dist-info/RECORD
