Metadata-Version: 2.1
Name: ceppy
Version: 1.0.1
Summary: 
Author: Erick Duarte
Author-email: erickod@gmail.com
Requires-Python: >=3.10,<3.12
Classifier: Programming Language :: Python :: 3
Classifier: Programming Language :: Python :: 3.10
Classifier: Programming Language :: Python :: 3.11
Requires-Dist: aiohttp (>=3.8.6,<4.0.0)
